aws/osml/data_intake/__init__.py
aws/osml/data_intake/bulk_processor.py
aws/osml/data_intake/image_processor.py
aws/osml/data_intake/ingest_processor.py
aws/osml/data_intake/processor_base.py
aws/osml/data_intake/managers/__init__.py
aws/osml/data_intake/managers/s3_manager.py
aws/osml/data_intake/managers/sns_manager.py
aws/osml/data_intake/utils/__init__.py
aws/osml/data_intake/utils/app_config.py
aws/osml/data_intake/utils/logger.py
osml_data_intake-1.1.2.dist-info/LICENSE
osml_data_intake-1.1.2.dist-info/METADATA
osml_data_intake-1.1.2.dist-info/WHEEL
osml_data_intake-1.1.2.dist-info/top_level.txt
osml_data_intake-1.1.2.dist-info/RECORD
