Metadata-Version: 2.1
Name: osml-data-intake
Version: 1.1.2
Summary: Package to run the osml image intake component service.
Author: Amazon Web Services
Author-email: aws-osml-admin@amazon.com
License: 
Project-URL: Source, https://github.com/aws-solutions-library-samples/osml-data-intake
Project-URL: Tracker, https://github.com/aws-solutions-library-samples/osml-data-intake/issues
Classifier: Programming Language :: Python :: 3
Classifier: Operating System :: OS Independent
Requires-Python: >=3.9
License-File: LICENSE
Provides-Extra: gdal
Requires-Dist: gdal >=3.8.3 ; extra == 'gdal'
Provides-Extra: test
Requires-Dist: tox ; extra == 'test'
